MANIFEST.in
fetchmail_data.xml
fetchmail_installer_view.xml
fetchmail_view.xml
setup.py
./__init__.py
./__openerp__.py
./fetchmail.py
./res_config.py
i18n/ar.po
i18n/bg.po
i18n/ca.po
i18n/cs.po
i18n/da.po
i18n/de.po
i18n/el.po
i18n/en_GB.po
i18n/es.po
i18n/es_CR.po
i18n/es_MX.po
i18n/es_VE.po
i18n/et.po
i18n/fetchmail.pot
i18n/fi.po
i18n/fr.po
i18n/gl.po
i18n/hr.po
i18n/hu.po
i18n/it.po
i18n/ja.po
i18n/ko.po
i18n/lt.po
i18n/lv.po
i18n/mk.po
i18n/mn.po
i18n/nb.po
i18n/nl.po
i18n/pl.po
i18n/pt.po
i18n/pt_BR.po
i18n/ro.po
i18n/ru.po
i18n/sl.po
i18n/sr.po
i18n/sr@latin.po
i18n/sv.po
i18n/tr.po
i18n/vi.po
i18n/zh_CN.po
images/1_email_servers.jpeg
openerp_fetchmail.egg-info/PKG-INFO
openerp_fetchmail.egg-info/SOURCES.txt
openerp_fetchmail.egg-info/dependency_links.txt
openerp_fetchmail.egg-info/requires.txt
openerp_fetchmail.egg-info/top_level.txt
security/ir.model.access.csv